{
  "backup_id": "inventory_db_wal_20250918_110133",
  "database": "inventory_db",
  "backup_type": "wal_incremental",
  "timestamp": "2025-09-18T11:01:33.191018",
  "lsn_start": "3/89486A38",
  "lsn_end": "3/8B000000",
  "wal_files_archived": [
    "000000190000000300000086.wal",
    "000000190000000300000087.wal",
    "000000190000000300000088.wal",
    "000000190000000300000089.wal",
    "00000019000000030000008A.wal"
  ],
  "timeline_id": 1,
  "server": "MCP1",
  "base_backup_reference": null
}